graft/__init__.py
graft/__main__.py
graft-0.0.1.dist-info/LICENSE
graft-0.0.1.dist-info/METADATA
graft-0.0.1.dist-info/WHEEL
graft-0.0.1.dist-info/top_level.txt
graft-0.0.1.dist-info/RECORD
