Metadata-Version: 2.1
Name: graft
Version: 0.0.1
Summary: they can graft a new hand onto the arm.
Home-page: https://github.com/chrizzFTD/graft
Author: Christian López Barrón
Author-email: chris.gfz@gmail.com
License: UNKNOWN
Download-URL: https://github.com/chrizzFTD/graft/releases/tag/0.0.1
Platform: UNKNOWN
Classifier: Programming Language :: Python :: 3.8
Provides-Extra: docs
Requires-Dist: sphinx-autodoc-typehints ; extra == 'docs'
Requires-Dist: sphinx-rtd-theme ; extra == 'docs'
